bip329/__init__.py
bip329/bip329_parser.py
bip329/bip329_writer.py
bip329/constants.py
bip329/encryption.py
bip329/validation_utils.py
bip329/tests/__init__.py
bip329/tests/test_bip329_encrypted_writer.py
bip329/tests/test_bip329_parser.py
bip329/tests/test_bip329_writer.py
bip329/tests/test_encryption.py
bip329/tests/test_label_validation.py
bip329-1.0.0.dist-info/licenses/LICENSE
bip329-1.0.0.dist-info/METADATA
bip329-1.0.0.dist-info/WHEEL
bip329-1.0.0.dist-info/top_level.txt
bip329-1.0.0.dist-info/RECORD
