Metadata-Version: 2.4
Name: bip329
Version: 1.0.0
License-File: LICENSE
Requires-Dist: py7zr
Dynamic: license-file
Dynamic: requires-dist
